LICENSE
MANIFEST.in
README.md
setup.py
liblearn/__init__.py
liblearn/github_api.py
liblearnpro.egg-info/PKG-INFO
liblearnpro.egg-info/SOURCES.txt
liblearnpro.egg-info/dependency_links.txt
liblearnpro.egg-info/not-zip-safe
liblearnpro.egg-info/requires.txt
liblearnpro.egg-info/top_level.txt