Metadata-Version: 2.1
Name: liblearnpro
Version: 0.2
Summary: Módulo de estudos para pytools do curso python pro
Home-page: https://github.com/serlus/libpythonpro
Author: Sergio Casas
Author-email: serluscasas@gmail.com
License: GNU AFFERO GENERAL PUBLIC LICENSE
Platform: UNKNOWN
Classifier: Development Status :: 2 - Pre-Alpha
Classifier: Environment :: Console
Classifier: Intended Audience :: Developers
Classifier: License :: OSI Approved :: GNU Affero General Public License v3 or later (AGPLv3+)
Classifier: Operating System :: OS Independent
Classifier: Programming Language :: Python
Classifier: Programming Language :: Python :: 3.6
Classifier: Framework :: Pytest
